jinja_terraform_output/__init__.py
jinja_terraform_output-1.0.0.dist-info/METADATA
jinja_terraform_output-1.0.0.dist-info/WHEEL
jinja_terraform_output-1.0.0.dist-info/top_level.txt
jinja_terraform_output-1.0.0.dist-info/RECORD
