Metadata-Version: 2.1
Name: jinja-terraform-output
Version: 1.0.0
Summary: A Jinja extension to fetch terraform state output versions
Author: Tathagata Paul
Author-email: tathagatapaul7@gmail.com
License: MIT
Platform: UNKNOWN
Requires-Dist: Jinja2 (<4)
Requires-Dist: requests (<3)
